module_reloader/__init__.py
module_reloader/module_reloader.py
tests/__init__.py
tests/test_module_reloader.py
module_reloader-0.1.0.dist-info/METADATA
module_reloader-0.1.0.dist-info/WHEEL
module_reloader-0.1.0.dist-info/top_level.txt
module_reloader-0.1.0.dist-info/RECORD
