Metadata-Version: 2.2
Name: module_reloader
Version: 0.1.0
Summary: A module reloader for Python
Home-page: https://github.com/odie/module_reloader
Author: Jonathan Shieh
Author-email: jonathan.shieh@gmail.com
Classifier: Programming Language :: Python :: 3
Classifier: License :: OSI Approved :: MIT License
Classifier: Operating System :: OS Independent
Requires-Python: >=3.7
Dynamic: author
Dynamic: author-email
Dynamic: classifier
Dynamic: description
Dynamic: description-content-type
Dynamic: home-page
Dynamic: requires-python
Dynamic: summary
